[
    {
        "index": 0,
        "zcr": 0.02978515625
    },
    {
        "index": 1,
        "zcr": 0.021240234375
    },
    {
        "index": 2,
        "zcr": 0.0146484375
    },
    {
        "index": 3,
        "zcr": 0.0146484375
    },
    {
        "index": 4,
        "zcr": 0.0166015625
    },
    {
        "index": 5,
        "zcr": 0.011474609375
    },
    {
        "index": 6,
        "zcr": 0.015869140625
    },
    {
        "index": 7,
        "zcr": 0.009521484375
    },
    {
        "index": 8,
        "zcr": 0.009521484375
    },
    {
        "index": 9,
        "zcr": 0.00634765625
    },
    {
        "index": 10,
        "zcr": 0.0166015625
    },
    {
        "index": 11,
        "zcr": 0.027099609375
    },
    {
        "index": 12,
        "zcr": 0.02880859375
    },
    {
        "index": 13,
        "zcr": 0.029052734375
    },
    {
        "index": 14,
        "zcr": 0.02294921875
    },
    {
        "index": 15,
        "zcr": 0.02734375
    },
    {
        "index": 16,
        "zcr": 0.028564453125
    },
    {
        "index": 17,
        "zcr": 0.025390625
    },
    {
        "index": 18,
        "zcr": 0.02734375
    },
    {
        "index": 19,
        "zcr": 0.024658203125
    },
    {
        "index": 20,
        "zcr": 0.0078125
    },
    {
        "index": 21,
        "zcr": 0.009033203125
    },
    {
        "index": 22,
        "zcr": 0.0166015625
    },
    {
        "index": 23,
        "zcr": 0.0146484375
    },
    {
        "index": 24,
        "zcr": 0.01220703125
    },
    {
        "index": 25,
        "zcr": 0.01318359375
    },
    {
        "index": 26,
        "zcr": 0.006591796875
    },
    {
        "index": 27,
        "zcr": 0.011962890625
    },
    {
        "index": 28,
        "zcr": 0.02001953125
    },
    {
        "index": 29,
        "zcr": 0.0205078125
    },
    {
        "index": 30,
        "zcr": 0.0205078125
    },
    {
        "index": 31,
        "zcr": 0.017578125
    },
    {
        "index": 32,
        "zcr": 0.0185546875
    },
    {
        "index": 33,
        "zcr": 0.030517578125
    },
    {
        "index": 34,
        "zcr": 0.021240234375
    },
    {
        "index": 35,
        "zcr": 0.011962890625
    },
    {
        "index": 36,
        "zcr": 0.01220703125
    },
    {
        "index": 37,
        "zcr": 0.00927734375
    },
    {
        "index": 38,
        "zcr": 0.012939453125
    },
    {
        "index": 39,
        "zcr": 0.009765625
    },
    {
        "index": 40,
        "zcr": 0.01025390625
    },
    {
        "index": 41,
        "zcr": 0.012939453125
    },
    {
        "index": 42,
        "zcr": 0.007080078125
    },
    {
        "index": 43,
        "zcr": 0.00634765625
    },
    {
        "index": 44,
        "zcr": 0.021240234375
    },
    {
        "index": 45,
        "zcr": 0.031005859375
    },
    {
        "index": 46,
        "zcr": 0.04052734375
    },
    {
        "index": 47,
        "zcr": 0.040283203125
    },
    {
        "index": 48,
        "zcr": 0.04541015625
    },
    {
        "index": 49,
        "zcr": 0.052490234375
    },
    {
        "index": 50,
        "zcr": 0.045166015625
    },
    {
        "index": 51,
        "zcr": 0.041015625
    },
    {
        "index": 52,
        "zcr": 0.045654296875
    },
    {
        "index": 53,
        "zcr": 0.048828125
    },
    {
        "index": 54,
        "zcr": 0.0439453125
    },
    {
        "index": 55,
        "zcr": 0.041259765625
    },
    {
        "index": 56,
        "zcr": 0.039794921875
    },
    {
        "index": 57,
        "zcr": 0.044189453125
    },
    {
        "index": 58,
        "zcr": 0.041748046875
    },
    {
        "index": 59,
        "zcr": 0.037353515625
    },
    {
        "index": 60,
        "zcr": 0.049560546875
    },
    {
        "index": 61,
        "zcr": 0.042236328125
    },
    {
        "index": 62,
        "zcr": 0.047607421875
    },
    {
        "index": 63,
        "zcr": 0.031982421875
    },
    {
        "index": 64,
        "zcr": 0.029541015625
    },
    {
        "index": 65,
        "zcr": 0.016357421875
    },
    {
        "index": 66,
        "zcr": 0.03271484375
    },
    {
        "index": 67,
        "zcr": 0.050048828125
    },
    {
        "index": 68,
        "zcr": 0.049560546875
    },
    {
        "index": 69,
        "zcr": 0.051025390625
    },
    {
        "index": 70,
        "zcr": 0.042236328125
    },
    {
        "index": 71,
        "zcr": 0.048095703125
    },
    {
        "index": 72,
        "zcr": 0.04541015625
    },
    {
        "index": 73,
        "zcr": 0.0439453125
    },
    {
        "index": 74,
        "zcr": 0.045166015625
    },
    {
        "index": 75,
        "zcr": 0.048583984375
    },
    {
        "index": 76,
        "zcr": 0.037353515625
    },
    {
        "index": 77,
        "zcr": 0.044921875
    },
    {
        "index": 78,
        "zcr": 0.050537109375
    },
    {
        "index": 79,
        "zcr": 0.038818359375
    },
    {
        "index": 80,
        "zcr": 0.041259765625
    },
    {
        "index": 81,
        "zcr": 0.047607421875
    },
    {
        "index": 82,
        "zcr": 0.046142578125
    },
    {
        "index": 83,
        "zcr": 0.052001953125
    },
    {
        "index": 84,
        "zcr": 0.02880859375
    },
    {
        "index": 85,
        "zcr": 0.025390625
    },
    {
        "index": 86,
        "zcr": 0.017578125
    },
    {
        "index": 87,
        "zcr": 0.036865234375
    },
    {
        "index": 88,
        "zcr": 0.032470703125
    },
    {
        "index": 89,
        "zcr": 0.048583984375
    },
    {
        "index": 90,
        "zcr": 0.051513671875
    },
    {
        "index": 91,
        "zcr": 0.044189453125
    },
    {
        "index": 92,
        "zcr": 0.04345703125
    },
    {
        "index": 93,
        "zcr": 0.044189453125
    },
    {
        "index": 94,
        "zcr": 0.04443359375
    },
    {
        "index": 95,
        "zcr": 0.046142578125
    },
    {
        "index": 96,
        "zcr": 0.043212890625
    },
    {
        "index": 97,
        "zcr": 0.035888671875
    },
    {
        "index": 98,
        "zcr": 0.046142578125
    },
    {
        "index": 99,
        "zcr": 0.04052734375
    },
    {
        "index": 100,
        "zcr": 0.038818359375
    },
    {
        "index": 101,
        "zcr": 0.043701171875
    },
    {
        "index": 102,
        "zcr": 0.05078125
    },
    {
        "index": 103,
        "zcr": 0.0478515625
    },
    {
        "index": 104,
        "zcr": 0.046142578125
    },
    {
        "index": 105,
        "zcr": 0.019287109375
    },
    {
        "index": 106,
        "zcr": 0.019287109375
    },
    {
        "index": 107,
        "zcr": 0.02099609375
    },
    {
        "index": 108,
        "zcr": 0.035888671875
    },
    {
        "index": 109,
        "zcr": 0.0361328125
    },
    {
        "index": 110,
        "zcr": 0.051513671875
    },
    {
        "index": 111,
        "zcr": 0.04345703125
    },
    {
        "index": 112,
        "zcr": 0.039794921875
    },
    {
        "index": 113,
        "zcr": 0.049072265625
    },
    {
        "index": 114,
        "zcr": 0.043701171875
    },
    {
        "index": 115,
        "zcr": 0.0419921875
    },
    {
        "index": 116,
        "zcr": 0.040771484375
    },
    {
        "index": 117,
        "zcr": 0.038818359375
    },
    {
        "index": 118,
        "zcr": 0.041748046875
    },
    {
        "index": 119,
        "zcr": 0.041259765625
    },
    {
        "index": 120,
        "zcr": 0.050537109375
    },
    {
        "index": 121,
        "zcr": 0.038330078125
    },
    {
        "index": 122,
        "zcr": 0.049560546875
    },
    {
        "index": 123,
        "zcr": 0.0419921875
    },
    {
        "index": 124,
        "zcr": 0.0439453125
    },
    {
        "index": 125,
        "zcr": 0.04833984375
    },
    {
        "index": 126,
        "zcr": 0.034423828125
    },
    {
        "index": 127,
        "zcr": 0.0322265625
    },
    {
        "index": 128,
        "zcr": 0.02099609375
    },
    {
        "index": 129,
        "zcr": 0.03515625
    },
    {
        "index": 130,
        "zcr": 0.038330078125
    },
    {
        "index": 131,
        "zcr": 0.047119140625
    },
    {
        "index": 132,
        "zcr": 0.046875
    },
    {
        "index": 133,
        "zcr": 0.04248046875
    },
    {
        "index": 134,
        "zcr": 0.04296875
    },
    {
        "index": 135,
        "zcr": 0.03955078125
    },
    {
        "index": 136,
        "zcr": 0.042724609375
    },
    {
        "index": 137,
        "zcr": 0.041259765625
    },
    {
        "index": 138,
        "zcr": 0.039306640625
    },
    {
        "index": 139,
        "zcr": 0.035400390625
    },
    {
        "index": 140,
        "zcr": 0.0458984375
    },
    {
        "index": 141,
        "zcr": 0.045654296875
    },
    {
        "index": 142,
        "zcr": 0.0390625
    },
    {
        "index": 143,
        "zcr": 0.046142578125
    },
    {
        "index": 144,
        "zcr": 0.040283203125
    },
    {
        "index": 145,
        "zcr": 0.04541015625
    },
    {
        "index": 146,
        "zcr": 0.0400390625
    },
    {
        "index": 147,
        "zcr": 0.01611328125
    },
    {
        "index": 148,
        "zcr": 0.017333984375
    },
    {
        "index": 149,
        "zcr": 0.022705078125
    },
    {
        "index": 150,
        "zcr": 0.045166015625
    },
    {
        "index": 151,
        "zcr": 0.030517578125
    },
    {
        "index": 152,
        "zcr": 0.043212890625
    },
    {
        "index": 153,
        "zcr": 0.04248046875
    },
    {
        "index": 154,
        "zcr": 0.04296875
    },
    {
        "index": 155,
        "zcr": 0.042724609375
    },
    {
        "index": 156,
        "zcr": 0.047607421875
    },
    {
        "index": 157,
        "zcr": 0.040283203125
    },
    {
        "index": 158,
        "zcr": 0.038330078125
    },
    {
        "index": 159,
        "zcr": 0.038818359375
    },
    {
        "index": 160,
        "zcr": 0.045654296875
    },
    {
        "index": 161,
        "zcr": 0.040283203125
    },
    {
        "index": 162,
        "zcr": 0.046142578125
    },
    {
        "index": 163,
        "zcr": 0.039794921875
    },
    {
        "index": 164,
        "zcr": 0.044189453125
    },
    {
        "index": 165,
        "zcr": 0.042236328125
    },
    {
        "index": 166,
        "zcr": 0.047119140625
    },
    {
        "index": 167,
        "zcr": 0.035888671875
    },
    {
        "index": 168,
        "zcr": 0.016845703125
    },
    {
        "index": 169,
        "zcr": 0.018310546875
    },
    {
        "index": 170,
        "zcr": 0.0244140625
    },
    {
        "index": 171,
        "zcr": 0.050048828125
    },
    {
        "index": 172,
        "zcr": 0.03955078125
    },
    {
        "index": 173,
        "zcr": 0.042724609375
    },
    {
        "index": 174,
        "zcr": 0.044677734375
    },
    {
        "index": 175,
        "zcr": 0.041015625
    },
    {
        "index": 176,
        "zcr": 0.041748046875
    },
    {
        "index": 177,
        "zcr": 0.040283203125
    },
    {
        "index": 178,
        "zcr": 0.044189453125
    },
    {
        "index": 179,
        "zcr": 0.044189453125
    },
    {
        "index": 180,
        "zcr": 0.041259765625
    },
    {
        "index": 181,
        "zcr": 0.035400390625
    },
    {
        "index": 182,
        "zcr": 0.04638671875
    },
    {
        "index": 183,
        "zcr": 0.0419921875
    },
    {
        "index": 184,
        "zcr": 0.042236328125
    },
    {
        "index": 185,
        "zcr": 0.041259765625
    },
    {
        "index": 186,
        "zcr": 0.044921875
    },
    {
        "index": 187,
        "zcr": 0.045166015625
    },
    {
        "index": 188,
        "zcr": 0.031982421875
    },
    {
        "index": 189,
        "zcr": 0.020263671875
    },
    {
        "index": 190,
        "zcr": 0.01123046875
    },
    {
        "index": 191,
        "zcr": 0.028076171875
    },
    {
        "index": 192,
        "zcr": 0.04052734375
    },
    {
        "index": 193,
        "zcr": 0.041259765625
    },
    {
        "index": 194,
        "zcr": 0.0478515625
    },
    {
        "index": 195,
        "zcr": 0.041748046875
    },
    {
        "index": 196,
        "zcr": 0.04296875
    },
    {
        "index": 197,
        "zcr": 0.0458984375
    },
    {
        "index": 198,
        "zcr": 0.044189453125
    },
    {
        "index": 199,
        "zcr": 0.027587890625
    },
    {
        "index": 200,
        "zcr": 0.07080078125
    },
    {
        "index": 201,
        "zcr": 0.092529296875
    },
    {
        "index": 202,
        "zcr": 0.01806640625
    },
    {
        "index": 203,
        "zcr": 0.05908203125
    },
    {
        "index": 204,
        "zcr": 0.04541015625
    },
    {
        "index": 205,
        "zcr": 0.0205078125
    },
    {
        "index": 206,
        "zcr": 0.025390625
    },
    {
        "index": 207,
        "zcr": 0.112548828125
    },
    {
        "index": 208,
        "zcr": 0.123291015625
    },
    {
        "index": 209,
        "zcr": 0.094482421875
    },
    {
        "index": 210,
        "zcr": 0.016357421875
    },
    {
        "index": 211,
        "zcr": 0.02880859375
    },
    {
        "index": 212,
        "zcr": 0.0048828125
    },
    {
        "index": 213,
        "zcr": 0.0068359375
    },
    {
        "index": 214,
        "zcr": 0.006103515625
    },
    {
        "index": 215,
        "zcr": 0.014892578125
    },
    {
        "index": 216,
        "zcr": 0.009765625
    },
    {
        "index": 217,
        "zcr": 0.00634765625
    },
    {
        "index": 218,
        "zcr": 0.013671875
    },
    {
        "index": 219,
        "zcr": 0.01123046875
    },
    {
        "index": 220,
        "zcr": 0.01318359375
    },
    {
        "index": 221,
        "zcr": 0.010498046875
    },
    {
        "index": 222,
        "zcr": 0.01171875
    },
    {
        "index": 223,
        "zcr": 0.02001953125
    },
    {
        "index": 224,
        "zcr": 0.01806640625
    },
    {
        "index": 225,
        "zcr": 0.015869140625
    },
    {
        "index": 226,
        "zcr": 0.00634765625
    },
    {
        "index": 227,
        "zcr": 0.009033203125
    },
    {
        "index": 228,
        "zcr": 0.013671875
    },
    {
        "index": 229,
        "zcr": 0.004150390625
    },
    {
        "index": 230,
        "zcr": 0.014404296875
    },
    {
        "index": 231,
        "zcr": 0.010498046875
    },
    {
        "index": 232,
        "zcr": 0.00927734375
    },
    {
        "index": 233,
        "zcr": 0.013427734375
    },
    {
        "index": 234,
        "zcr": 0.0087890625
    },
    {
        "index": 235,
        "zcr": 0.01708984375
    },
    {
        "index": 236,
        "zcr": 0.030029296875
    },
    {
        "index": 237,
        "zcr": 0.02880859375
    },
    {
        "index": 238,
        "zcr": 0.016845703125
    },
    {
        "index": 239,
        "zcr": 0.010986328125
    },
    {
        "index": 240,
        "zcr": 0.019287109375
    },
    {
        "index": 241,
        "zcr": 0.00439453125
    },
    {
        "index": 242,
        "zcr": 0.003662109375
    },
    {
        "index": 243,
        "zcr": 0.00341796875
    },
    {
        "index": 244,
        "zcr": 0.00634765625
    },
    {
        "index": 245,
        "zcr": 0.00439453125
    },
    {
        "index": 246,
        "zcr": 0.02880859375
    },
    {
        "index": 247,
        "zcr": 0.0283203125
    },
    {
        "index": 248,
        "zcr": 0.032470703125
    },
    {
        "index": 249,
        "zcr": 0.027587890625
    },
    {
        "index": 250,
        "zcr": 0.02978515625
    },
    {
        "index": 251,
        "zcr": 0.018310546875
    },
    {
        "index": 252,
        "zcr": 0.007568359375
    },
    {
        "index": 253,
        "zcr": 0.007568359375
    },
    {
        "index": 254,
        "zcr": 0.009765625
    },
    {
        "index": 255,
        "zcr": 0.007568359375
    },
    {
        "index": 256,
        "zcr": 0.01611328125
    },
    {
        "index": 257,
        "zcr": 0.00927734375
    },
    {
        "index": 258,
        "zcr": 0.00830078125
    },
    {
        "index": 259,
        "zcr": 0.00634765625
    },
    {
        "index": 260,
        "zcr": 0.010498046875
    },
    {
        "index": 261,
        "zcr": 0.01708984375
    },
    {
        "index": 262,
        "zcr": 0.00439453125
    },
    {
        "index": 263,
        "zcr": 0.01171875
    },
    {
        "index": 264,
        "zcr": 0.021484375
    },
    {
        "index": 265,
        "zcr": 0.02197265625
    },
    {
        "index": 266,
        "zcr": 0.023681640625
    },
    {
        "index": 267,
        "zcr": 0.013427734375
    },
    {
        "index": 268,
        "zcr": 0.00537109375
    },
    {
        "index": 269,
        "zcr": 0.01171875
    },
    {
        "index": 270,
        "zcr": 0.015380859375
    },
    {
        "index": 271,
        "zcr": 0.00244140625
    },
    {
        "index": 272,
        "zcr": 0.016357421875
    },
    {
        "index": 273,
        "zcr": 0.009765625
    },
    {
        "index": 274,
        "zcr": 0.00830078125
    },
    {
        "index": 275,
        "zcr": 0.015380859375
    },
    {
        "index": 276,
        "zcr": 0.00927734375
    },
    {
        "index": 277,
        "zcr": 0.02392578125
    },
    {
        "index": 278,
        "zcr": 0.034423828125
    },
    {
        "index": 279,
        "zcr": 0.033447265625
    },
    {
        "index": 280,
        "zcr": 0.011962890625
    },
    {
        "index": 281,
        "zcr": 0.00830078125
    },
    {
        "index": 282,
        "zcr": 0.01611328125
    },
    {
        "index": 283,
        "zcr": 0.002197265625
    },
    {
        "index": 284,
        "zcr": 0.00341796875
    },
    {
        "index": 285,
        "zcr": 0.005126953125
    },
    {
        "index": 286,
        "zcr": 0.003662109375
    },
    {
        "index": 287,
        "zcr": 0.00927734375
    },
    {
        "index": 288,
        "zcr": 0.02978515625
    },
    {
        "index": 289,
        "zcr": 0.0302734375
    },
    {
        "index": 290,
        "zcr": 0.032470703125
    },
    {
        "index": 291,
        "zcr": 0.028076171875
    },
    {
        "index": 292,
        "zcr": 0.031005859375
    },
    {
        "index": 293,
        "zcr": 0.009033203125
    },
    {
        "index": 294,
        "zcr": 0.011474609375
    },
    {
        "index": 295,
        "zcr": 0.013427734375
    },
    {
        "index": 296,
        "zcr": 0.010498046875
    },
    {
        "index": 297,
        "zcr": 0.009521484375
    },
    {
        "index": 298,
        "zcr": 0.013916015625
    },
    {
        "index": 299,
        "zcr": 0.01123046875
    },
    {
        "index": 300,
        "zcr": 0.0068359375
    },
    {
        "index": 301,
        "zcr": 0.00927734375
    },
    {
        "index": 302,
        "zcr": 0.009521484375
    },
    {
        "index": 303,
        "zcr": 0.017333984375
    },
    {
        "index": 304,
        "zcr": 0.0087890625
    },
    {
        "index": 305,
        "zcr": 0.0087890625
    },
    {
        "index": 306,
        "zcr": 0.018310546875
    },
    {
        "index": 307,
        "zcr": 0.024658203125
    },
    {
        "index": 308,
        "zcr": 0.01708984375
    },
    {
        "index": 309,
        "zcr": 0.00830078125
    },
    {
        "index": 310,
        "zcr": 0.00830078125
    },
    {
        "index": 311,
        "zcr": 0.012939453125
    },
    {
        "index": 312,
        "zcr": 0.011474609375
    },
    {
        "index": 313,
        "zcr": 0.01416015625
    },
    {
        "index": 314,
        "zcr": 0.005859375
    },
    {
        "index": 315,
        "zcr": 0.010009765625
    },
    {
        "index": 316,
        "zcr": 0.01025390625
    },
    {
        "index": 317,
        "zcr": 0.012939453125
    },
    {
        "index": 318,
        "zcr": 0.015869140625
    },
    {
        "index": 319,
        "zcr": 0.0302734375
    },
    {
        "index": 320,
        "zcr": 0.03466796875
    },
    {
        "index": 321,
        "zcr": 0.027587890625
    },
    {
        "index": 322,
        "zcr": 0.01171875
    },
    {
        "index": 323,
        "zcr": 0.00732421875
    },
    {
        "index": 324,
        "zcr": 0.0185546875
    },
    {
        "index": 325,
        "zcr": 0.00341796875
    },
    {
        "index": 326,
        "zcr": 0.003662109375
    },
    {
        "index": 327,
        "zcr": 0.00390625
    },
    {
        "index": 328,
        "zcr": 0.005126953125
    },
    {
        "index": 329,
        "zcr": 0.0205078125
    },
    {
        "index": 330,
        "zcr": 0.02978515625
    },
    {
        "index": 331,
        "zcr": 0.030029296875
    },
    {
        "index": 332,
        "zcr": 0.02978515625
    },
    {
        "index": 333,
        "zcr": 0.029296875
    },
    {
        "index": 334,
        "zcr": 0.0302734375
    },
    {
        "index": 335,
        "zcr": 0.009765625
    },
    {
        "index": 336,
        "zcr": 0.010498046875
    },
    {
        "index": 337,
        "zcr": 0.011474609375
    },
    {
        "index": 338,
        "zcr": 0.01171875
    },
    {
        "index": 339,
        "zcr": 0.01416015625
    },
    {
        "index": 340,
        "zcr": 0.01318359375
    },
    {
        "index": 341,
        "zcr": 0.0087890625
    },
    {
        "index": 342,
        "zcr": 0.006103515625
    },
    {
        "index": 343,
        "zcr": 0.010009765625
    },
    {
        "index": 344,
        "zcr": 0.010498046875
    },
    {
        "index": 345,
        "zcr": 0.014892578125
    },
    {
        "index": 346,
        "zcr": 0.0087890625
    },
    {
        "index": 347,
        "zcr": 0.010498046875
    },
    {
        "index": 348,
        "zcr": 0.0205078125
    },
    {
        "index": 349,
        "zcr": 0.02099609375
    },
    {
        "index": 350,
        "zcr": 0.017333984375
    },
    {
        "index": 351,
        "zcr": 0.00732421875
    },
    {
        "index": 352,
        "zcr": 0.00830078125
    },
    {
        "index": 353,
        "zcr": 0.01513671875
    },
    {
        "index": 354,
        "zcr": 0.005859375
    },
    {
        "index": 355,
        "zcr": 0.016357421875
    },
    {
        "index": 356,
        "zcr": 0.00537109375
    },
    {
        "index": 357,
        "zcr": 0.010009765625
    },
    {
        "index": 358,
        "zcr": 0.01611328125
    },
    {
        "index": 359,
        "zcr": 0.013427734375
    },
    {
        "index": 360,
        "zcr": 0.015625
    },
    {
        "index": 361,
        "zcr": 0.030029296875
    },
    {
        "index": 362,
        "zcr": 0.034423828125
    },
    {
        "index": 363,
        "zcr": 0.019287109375
    },
    {
        "index": 364,
        "zcr": 0.01171875
    },
    {
        "index": 365,
        "zcr": 0.014892578125
    },
    {
        "index": 366,
        "zcr": 0.007080078125
    },
    {
        "index": 367,
        "zcr": 0.0029296875
    },
    {
        "index": 368,
        "zcr": 0.001953125
    },
    {
        "index": 369,
        "zcr": 0.00439453125
    },
    {
        "index": 370,
        "zcr": 0.004638671875
    },
    {
        "index": 371,
        "zcr": 0.027099609375
    },
    {
        "index": 372,
        "zcr": 0.031494140625
    },
    {
        "index": 373,
        "zcr": 0.03271484375
    },
    {
        "index": 374,
        "zcr": 0.02783203125
    },
    {
        "index": 375,
        "zcr": 0.02734375
    },
    {
        "index": 376,
        "zcr": 0.020263671875
    },
    {
        "index": 377,
        "zcr": 0.01220703125
    },
    {
        "index": 378,
        "zcr": 0.007080078125
    },
    {
        "index": 379,
        "zcr": 0.0146484375
    },
    {
        "index": 380,
        "zcr": 0.011474609375
    },
    {
        "index": 381,
        "zcr": 0.013916015625
    },
    {
        "index": 382,
        "zcr": 0.0078125
    },
    {
        "index": 383,
        "zcr": 0.01171875
    },
    {
        "index": 384,
        "zcr": 0.009033203125
    },
    {
        "index": 385,
        "zcr": 0.00927734375
    },
    {
        "index": 386,
        "zcr": 0.019287109375
    },
    {
        "index": 387,
        "zcr": 0.005126953125
    },
    {
        "index": 388,
        "zcr": 0.00927734375
    },
    {
        "index": 389,
        "zcr": 0.0205078125
    },
    {
        "index": 390,
        "zcr": 0.024169921875
    },
    {
        "index": 391,
        "zcr": 0.020751953125
    },
    {
        "index": 392,
        "zcr": 0.01025390625
    },
    {
        "index": 393,
        "zcr": 0.0107421875
    },
    {
        "index": 394,
        "zcr": 0.007080078125
    },
    {
        "index": 395,
        "zcr": 0.018310546875
    },
    {
        "index": 396,
        "zcr": 0.00341796875
    },
    {
        "index": 397,
        "zcr": 0.01806640625
    },
    {
        "index": 398,
        "zcr": 0.00830078125
    },
    {
        "index": 399,
        "zcr": 0.009765625
    },
    {
        "index": 400,
        "zcr": 0.011474609375
    },
    {
        "index": 401,
        "zcr": 0.010986328125
    },
    {
        "index": 402,
        "zcr": 0.02001953125
    },
    {
        "index": 403,
        "zcr": 0.035888671875
    },
    {
        "index": 404,
        "zcr": 0.033447265625
    },
    {
        "index": 405,
        "zcr": 0.00830078125
    },
    {
        "index": 406,
        "zcr": 0.00732421875
    },
    {
        "index": 407,
        "zcr": 0.0126953125
    },
    {
        "index": 408,
        "zcr": 0.00390625
    },
    {
        "index": 409,
        "zcr": 0.005615234375
    },
    {
        "index": 410,
        "zcr": 0.021240234375
    },
    {
        "index": 411,
        "zcr": 0.02490234375
    },
    {
        "index": 412,
        "zcr": 0.02685546875
    },
    {
        "index": 413,
        "zcr": 0.033935546875
    },
    {
        "index": 414,
        "zcr": 0.035888671875
    },
    {
        "index": 415,
        "zcr": 0.03369140625
    },
    {
        "index": 416,
        "zcr": 0.032958984375
    },
    {
        "index": 417,
        "zcr": 0.03271484375
    },
    {
        "index": 418,
        "zcr": 0.01708984375
    },
    {
        "index": 419,
        "zcr": 0.015380859375
    },
    {
        "index": 420,
        "zcr": 0.012451171875
    },
    {
        "index": 421,
        "zcr": 0.01416015625
    },
    {
        "index": 422,
        "zcr": 0.0126953125
    },
    {
        "index": 423,
        "zcr": 0.014404296875
    },
    {
        "index": 424,
        "zcr": 0.015869140625
    },
    {
        "index": 425,
        "zcr": 0.013916015625
    },
    {
        "index": 426,
        "zcr": 0.009765625
    },
    {
        "index": 427,
        "zcr": 0.0068359375
    },
    {
        "index": 428,
        "zcr": 0.02099609375
    },
    {
        "index": 429,
        "zcr": 0.00439453125
    },
    {
        "index": 430,
        "zcr": 0.0126953125
    },
    {
        "index": 431,
        "zcr": 0.02294921875
    },
    {
        "index": 432,
        "zcr": 0.022705078125
    },
    {
        "index": 433,
        "zcr": 0.02294921875
    },
    {
        "index": 434,
        "zcr": 0.008056640625
    },
    {
        "index": 435,
        "zcr": 0.0048828125
    },
    {
        "index": 436,
        "zcr": 0.01416015625
    },
    {
        "index": 437,
        "zcr": 0.008056640625
    },
    {
        "index": 438,
        "zcr": 0.01171875
    },
    {
        "index": 439,
        "zcr": 0.005615234375
    },
    {
        "index": 440,
        "zcr": 0.007080078125
    },
    {
        "index": 441,
        "zcr": 0.0107421875
    },
    {
        "index": 442,
        "zcr": 0.01416015625
    },
    {
        "index": 443,
        "zcr": 0.009521484375
    },
    {
        "index": 444,
        "zcr": 0.02880859375
    },
    {
        "index": 445,
        "zcr": 0.034912109375
    },
    {
        "index": 446,
        "zcr": 0.02294921875
    },
    {
        "index": 447,
        "zcr": 0.004150390625
    },
    {
        "index": 448,
        "zcr": 0.00390625
    },
    {
        "index": 449,
        "zcr": 0.01513671875
    },
    {
        "index": 450,
        "zcr": 0.00830078125
    },
    {
        "index": 451,
        "zcr": 0.0087890625
    },
    {
        "index": 452,
        "zcr": 0.02587890625
    },
    {
        "index": 453,
        "zcr": 0.030517578125
    },
    {
        "index": 454,
        "zcr": 0.027099609375
    },
    {
        "index": 455,
        "zcr": 0.0341796875
    },
    {
        "index": 456,
        "zcr": 0.03759765625
    },
    {
        "index": 457,
        "zcr": 0.0361328125
    },
    {
        "index": 458,
        "zcr": 0.03125
    },
    {
        "index": 459,
        "zcr": 0.026611328125
    },
    {
        "index": 460,
        "zcr": 0.00732421875
    },
    {
        "index": 461,
        "zcr": 0.01123046875
    },
    {
        "index": 462,
        "zcr": 0.01513671875
    },
    {
        "index": 463,
        "zcr": 0.01513671875
    },
    {
        "index": 464,
        "zcr": 0.009521484375
    },
    {
        "index": 465,
        "zcr": 0.01318359375
    },
    {
        "index": 466,
        "zcr": 0.01025390625
    },
    {
        "index": 467,
        "zcr": 0.008056640625
    },
    {
        "index": 468,
        "zcr": 0.012451171875
    },
    {
        "index": 469,
        "zcr": 0.009521484375
    },
    {
        "index": 470,
        "zcr": 0.015380859375
    },
    {
        "index": 471,
        "zcr": 0.014892578125
    },
    {
        "index": 472,
        "zcr": 0.015625
    },
    {
        "index": 473,
        "zcr": 0.017578125
    },
    {
        "index": 474,
        "zcr": 0.019287109375
    },
    {
        "index": 475,
        "zcr": 0.013671875
    },
    {
        "index": 476,
        "zcr": 0.007568359375
    },
    {
        "index": 477,
        "zcr": 0.00537109375
    },
    {
        "index": 478,
        "zcr": 0.014892578125
    },
    {
        "index": 479,
        "zcr": 0.0048828125
    },
    {
        "index": 480,
        "zcr": 0.01708984375
    },
    {
        "index": 481,
        "zcr": 0.0068359375
    },
    {
        "index": 482,
        "zcr": 0.005615234375
    },
    {
        "index": 483,
        "zcr": 0.01318359375
    },
    {
        "index": 484,
        "zcr": 0.0126953125
    },
    {
        "index": 485,
        "zcr": 0.0166015625
    },
    {
        "index": 486,
        "zcr": 0.032470703125
    },
    {
        "index": 487,
        "zcr": 0.03125
    },
    {
        "index": 488,
        "zcr": 0.01611328125
    },
    {
        "index": 489,
        "zcr": 0.0068359375
    },
    {
        "index": 490,
        "zcr": 0.0087890625
    },
    {
        "index": 491,
        "zcr": 0.008544921875
    },
    {
        "index": 492,
        "zcr": 0.0078125
    },
    {
        "index": 493,
        "zcr": 0.014892578125
    },
    {
        "index": 494,
        "zcr": 0.02783203125
    },
    {
        "index": 495,
        "zcr": 0.028076171875
    },
    {
        "index": 496,
        "zcr": 0.029052734375
    },
    {
        "index": 497,
        "zcr": 0.03076171875
    },
    {
        "index": 498,
        "zcr": 0.035888671875
    },
    {
        "index": 499,
        "zcr": 0.033935546875
    },
    {
        "index": 500,
        "zcr": 0.030517578125
    },
    {
        "index": 501,
        "zcr": 0.0263671875
    },
    {
        "index": 502,
        "zcr": 0.00830078125
    },
    {
        "index": 503,
        "zcr": 0.013671875
    },
    {
        "index": 504,
        "zcr": 0.012939453125
    },
    {
        "index": 505,
        "zcr": 0.0126953125
    },
    {
        "index": 506,
        "zcr": 0.014404296875
    },
    {
        "index": 507,
        "zcr": 0.017822265625
    },
    {
        "index": 508,
        "zcr": 0.008056640625
    },
    {
        "index": 509,
        "zcr": 0.0078125
    },
    {
        "index": 510,
        "zcr": 0.01416015625
    },
    {
        "index": 511,
        "zcr": 0.015625
    },
    {
        "index": 512,
        "zcr": 0.009521484375
    },
    {
        "index": 513,
        "zcr": 0.009033203125
    },
    {
        "index": 514,
        "zcr": 0.02001953125
    },
    {
        "index": 515,
        "zcr": 0.01806640625
    },
    {
        "index": 516,
        "zcr": 0.01513671875
    },
    {
        "index": 517,
        "zcr": 0.01171875
    },
    {
        "index": 518,
        "zcr": 0.0048828125
    },
    {
        "index": 519,
        "zcr": 0.0078125
    },
    {
        "index": 520,
        "zcr": 0.014892578125
    },
    {
        "index": 521,
        "zcr": 0.00146484375
    },
    {
        "index": 522,
        "zcr": 0.012939453125
    },
    {
        "index": 523,
        "zcr": 0.009521484375
    },
    {
        "index": 524,
        "zcr": 0.009033203125
    },
    {
        "index": 525,
        "zcr": 0.01708984375
    },
    {
        "index": 525,
        "zcr": 0.01708984375
    },
    {
        "index": 525,
        "zcr": 0.01708984375
    },
    {
        "index": 528,
        "zcr": 0.03369140625
    },
    {
        "index": 529,
        "zcr": 0.03857421875
    },
    {
        "index": 530,
        "zcr": 0.035400390625
    },
    {
        "index": 531,
        "zcr": 0.024169921875
    },
    {
        "index": 532,
        "zcr": 0.030517578125
    },
    {
        "index": 533,
        "zcr": 0.02783203125
    },
    {
        "index": 534,
        "zcr": 0.09814453125
    },
    {
        "index": 535,
        "zcr": 0.048583984375
    },
    {
        "index": 536,
        "zcr": 0.0458984375
    },
    {
        "index": 537,
        "zcr": 0.058349609375
    },
    {
        "index": 538,
        "zcr": 0.02978515625
    },
    {
        "index": 539,
        "zcr": 0.03173828125
    },
    {
        "index": 540,
        "zcr": 0.0537109375
    },
    {
        "index": 541,
        "zcr": 0.06396484375
    },
    {
        "index": 542,
        "zcr": 0.072998046875
    },
    {
        "index": 543,
        "zcr": 0.024169921875
    },
    {
        "index": 544,
        "zcr": 0.0556640625
    },
    {
        "index": 545,
        "zcr": 0.075439453125
    },
    {
        "index": 546,
        "zcr": 0.043701171875
    },
    {
        "index": 547,
        "zcr": 0.01318359375
    },
    {
        "index": 548,
        "zcr": 0.01513671875
    },
    {
        "index": 549,
        "zcr": 0.008056640625
    },
    {
        "index": 550,
        "zcr": 0.005859375
    },
    {
        "index": 551,
        "zcr": 0.012451171875
    },
    {
        "index": 552,
        "zcr": 0.010009765625
    },
    {
        "index": 553,
        "zcr": 0.01220703125
    },
    {
        "index": 554,
        "zcr": 0.047119140625
    },
    {
        "index": 555,
        "zcr": 0.103759765625
    },
    {
        "index": 556,
        "zcr": 0.044921875
    },
    {
        "index": 557,
        "zcr": 0.024169921875
    },
    {
        "index": 558,
        "zcr": 0.020751953125
    },
    {
        "index": 559,
        "zcr": 0.009033203125
    },
    {
        "index": 560,
        "zcr": 0.00732421875
    },
    {
        "index": 561,
        "zcr": 0.015869140625
    },
    {
        "index": 562,
        "zcr": 0.01171875
    },
    {
        "index": 563,
        "zcr": 0.013427734375
    },
    {
        "index": 564,
        "zcr": 0.00537109375
    },
    {
        "index": 565,
        "zcr": 0.009765625
    },
    {
        "index": 566,
        "zcr": 0.0029296875
    },
    {
        "index": 567,
        "zcr": 0.0087890625
    },
    {
        "index": 568,
        "zcr": 0.011962890625
    },
    {
        "index": 569,
        "zcr": 0.0263671875
    },
    {
        "index": 570,
        "zcr": 0.03271484375
    },
    {
        "index": 571,
        "zcr": 0.030029296875
    },
    {
        "index": 572,
        "zcr": 0.0205078125
    },
    {
        "index": 573,
        "zcr": 0.04248046875
    },
    {
        "index": 574,
        "zcr": 0.029541015625
    },
    {
        "index": 575,
        "zcr": 0.033935546875
    },
    {
        "index": 576,
        "zcr": 0.0810546875
    },
    {
        "index": 577,
        "zcr": 0.041259765625
    },
    {
        "index": 578,
        "zcr": 0.028076171875
    },
    {
        "index": 579,
        "zcr": 0.030029296875
    },
    {
        "index": 580,
        "zcr": 0.034423828125
    },
    {
        "index": 581,
        "zcr": 0.036865234375
    },
    {
        "index": 582,
        "zcr": 0.034423828125
    },
    {
        "index": 583,
        "zcr": 0.033203125
    },
    {
        "index": 584,
        "zcr": 0.03173828125
    },
    {
        "index": 585,
        "zcr": 0.004150390625
    },
    {
        "index": 586,
        "zcr": 0.00927734375
    },
    {
        "index": 587,
        "zcr": 0.00341796875
    },
    {
        "index": 588,
        "zcr": 0.009033203125
    },
    {
        "index": 589,
        "zcr": 0.010009765625
    },
    {
        "index": 590,
        "zcr": 0.010009765625
    },
    {
        "index": 591,
        "zcr": 0.0078125
    },
    {
        "index": 592,
        "zcr": 0.0126953125
    },
    {
        "index": 593,
        "zcr": 0.01025390625
    },
    {
        "index": 594,
        "zcr": 0.0078125
    },
    {
        "index": 595,
        "zcr": 0.0205078125
    },
    {
        "index": 596,
        "zcr": 0.080078125
    },
    {
        "index": 597,
        "zcr": 0.10107421875
    },
    {
        "index": 598,
        "zcr": 0.033935546875
    },
    {
        "index": 599,
        "zcr": 0.0166015625
    },
    {
        "index": 600,
        "zcr": 0.021240234375
    },
    {
        "index": 601,
        "zcr": 0.0068359375
    },
    {
        "index": 602,
        "zcr": 0.005859375
    },
    {
        "index": 603,
        "zcr": 0.01611328125
    },
    {
        "index": 604,
        "zcr": 0.005859375
    },
    {
        "index": 605,
        "zcr": 0.017822265625
    },
    {
        "index": 606,
        "zcr": 0.00439453125
    },
    {
        "index": 607,
        "zcr": 0.008544921875
    },
    {
        "index": 608,
        "zcr": 0.00390625
    },
    {
        "index": 609,
        "zcr": 0.0078125
    },
    {
        "index": 610,
        "zcr": 0.00830078125
    },
    {
        "index": 611,
        "zcr": 0.027587890625
    },
    {
        "index": 612,
        "zcr": 0.03369140625
    },
    {
        "index": 613,
        "zcr": 0.03173828125
    },
    {
        "index": 614,
        "zcr": 0.029052734375
    },
    {
        "index": 615,
        "zcr": 0.023681640625
    },
    {
        "index": 616,
        "zcr": 0.023681640625
    },
    {
        "index": 617,
        "zcr": 0.0859375
    },
    {
        "index": 618,
        "zcr": 0.068359375
    },
    {
        "index": 619,
        "zcr": 0.031982421875
    },
    {
        "index": 620,
        "zcr": 0.025634765625
    },
    {
        "index": 621,
        "zcr": 0.0283203125
    },
    {
        "index": 622,
        "zcr": 0.03125
    },
    {
        "index": 623,
        "zcr": 0.033447265625
    },
    {
        "index": 624,
        "zcr": 0.032958984375
    },
    {
        "index": 625,
        "zcr": 0.030029296875
    },
    {
        "index": 626,
        "zcr": 0.025390625
    },
    {
        "index": 627,
        "zcr": 0.005126953125
    },
    {
        "index": 628,
        "zcr": 0.00341796875
    },
    {
        "index": 629,
        "zcr": 0.005859375
    },
    {
        "index": 630,
        "zcr": 0.006103515625
    },
    {
        "index": 631,
        "zcr": 0.0107421875
    },
    {
        "index": 632,
        "zcr": 0.01318359375
    },
    {
        "index": 633,
        "zcr": 0.0107421875
    },
    {
        "index": 634,
        "zcr": 0.010986328125
    },
    {
        "index": 635,
        "zcr": 0.01025390625
    },
    {
        "index": 636,
        "zcr": 0.012939453125
    },
    {
        "index": 637,
        "zcr": 0.02392578125
    },
    {
        "index": 638,
        "zcr": 0.09423828125
    },
    {
        "index": 639,
        "zcr": 0.074951171875
    },
    {
        "index": 640,
        "zcr": 0.025634765625
    },
    {
        "index": 641,
        "zcr": 0.02099609375
    },
    {
        "index": 642,
        "zcr": 0.012451171875
    },
    {
        "index": 643,
        "zcr": 0.010986328125
    },
    {
        "index": 644,
        "zcr": 0.00634765625
    },
    {
        "index": 645,
        "zcr": 0.013427734375
    },
    {
        "index": 646,
        "zcr": 0.00341796875
    },
    {
        "index": 647,
        "zcr": 0.0185546875
    },
    {
        "index": 648,
        "zcr": 0.009521484375
    },
    {
        "index": 649,
        "zcr": 0.003173828125
    },
    {
        "index": 650,
        "zcr": 0.00390625
    },
    {
        "index": 651,
        "zcr": 0.0087890625
    },
    {
        "index": 652,
        "zcr": 0.009765625
    },
    {
        "index": 653,
        "zcr": 0.033447265625
    },
    {
        "index": 654,
        "zcr": 0.032470703125
    },
    {
        "index": 655,
        "zcr": 0.02734375
    },
    {
        "index": 656,
        "zcr": 0.03515625
    },
    {
        "index": 657,
        "zcr": 0.029541015625
    },
    {
        "index": 658,
        "zcr": 0.02197265625
    },
    {
        "index": 659,
        "zcr": 0.0732421875
    },
    {
        "index": 660,
        "zcr": 0.06103515625
    },
    {
        "index": 661,
        "zcr": 0.029541015625
    },
    {
        "index": 662,
        "zcr": 0.02783203125
    },
    {
        "index": 663,
        "zcr": 0.03515625
    },
    {
        "index": 664,
        "zcr": 0.0322265625
    },
    {
        "index": 665,
        "zcr": 0.0302734375
    },
    {
        "index": 666,
        "zcr": 0.032470703125
    },
    {
        "index": 667,
        "zcr": 0.030517578125
    },
    {
        "index": 668,
        "zcr": 0.0166015625
    },
    {
        "index": 669,
        "zcr": 0.00439453125
    },
    {
        "index": 670,
        "zcr": 0.005859375
    },
    {
        "index": 671,
        "zcr": 0.0048828125
    },
    {
        "index": 672,
        "zcr": 0.005859375
    },
    {
        "index": 673,
        "zcr": 0.00830078125
    },
    {
        "index": 674,
        "zcr": 0.008056640625
    },
    {
        "index": 675,
        "zcr": 0.0048828125
    },
    {
        "index": 676,
        "zcr": 0.00537109375
    },
    {
        "index": 677,
        "zcr": 0.00634765625
    },
    {
        "index": 678,
        "zcr": 0.013916015625
    },
    {
        "index": 679,
        "zcr": 0.04638671875
    },
    {
        "index": 680,
        "zcr": 0.099853515625
    },
    {
        "index": 681,
        "zcr": 0.04443359375
    },
    {
        "index": 682,
        "zcr": 0.024658203125
    },
    {
        "index": 683,
        "zcr": 0.0234375
    },
    {
        "index": 684,
        "zcr": 0.01123046875
    },
    {
        "index": 685,
        "zcr": 0.0078125
    },
    {
        "index": 686,
        "zcr": 0.00927734375
    },
    {
        "index": 687,
        "zcr": 0.009033203125
    },
    {
        "index": 688,
        "zcr": 0.0107421875
    },
    {
        "index": 689,
        "zcr": 0.009521484375
    },
    {
        "index": 690,
        "zcr": 0.009765625
    },
    {
        "index": 691,
        "zcr": 0.005859375
    },
    {
        "index": 692,
        "zcr": 0.009033203125
    },
    {
        "index": 693,
        "zcr": 0.015869140625
    },
    {
        "index": 694,
        "zcr": 0.0263671875
    },
    {
        "index": 695,
        "zcr": 0.041015625
    },
    {
        "index": 696,
        "zcr": 0.031982421875
    },
    {
        "index": 697,
        "zcr": 0.029052734375
    },
    {
        "index": 698,
        "zcr": 0.02880859375
    },
    {
        "index": 699,
        "zcr": 0.03369140625
    },
    {
        "index": 700,
        "zcr": 0.06396484375
    },
    {
        "index": 701,
        "zcr": 0.08984375
    },
    {
        "index": 702,
        "zcr": 0.04931640625
    },
    {
        "index": 703,
        "zcr": 0.031982421875
    },
    {
        "index": 704,
        "zcr": 0.027099609375
    },
    {
        "index": 705,
        "zcr": 0.031494140625
    },
    {
        "index": 706,
        "zcr": 0.033935546875
    },
    {
        "index": 707,
        "zcr": 0.034912109375
    },
    {
        "index": 708,
        "zcr": 0.033447265625
    },
    {
        "index": 709,
        "zcr": 0.02978515625
    },
    {
        "index": 710,
        "zcr": 0.0048828125
    },
    {
        "index": 711,
        "zcr": 0.0048828125
    },
    {
        "index": 712,
        "zcr": 0.0048828125
    },
    {
        "index": 713,
        "zcr": 0.004150390625
    },
    {
        "index": 714,
        "zcr": 0.00927734375
    },
    {
        "index": 715,
        "zcr": 0.00634765625
    },
    {
        "index": 716,
        "zcr": 0.01171875
    },
    {
        "index": 717,
        "zcr": 0.004150390625
    },
    {
        "index": 718,
        "zcr": 0.00634765625
    },
    {
        "index": 719,
        "zcr": 0.00537109375
    },
    {
        "index": 720,
        "zcr": 0.020751953125
    },
    {
        "index": 721,
        "zcr": 0.057861328125
    },
    {
        "index": 722,
        "zcr": 0.0947265625
    },
    {
        "index": 723,
        "zcr": 0.0283203125
    },
    {
        "index": 724,
        "zcr": 0.0224609375
    },
    {
        "index": 725,
        "zcr": 0.017333984375
    },
    {
        "index": 726,
        "zcr": 0.00830078125
    },
    {
        "index": 727,
        "zcr": 0.005859375
    },
    {
        "index": 728,
        "zcr": 0.015869140625
    },
    {
        "index": 729,
        "zcr": 0.006103515625
    },
    {
        "index": 730,
        "zcr": 0.014892578125
    },
    {
        "index": 731,
        "zcr": 0.008056640625
    },
    {
        "index": 732,
        "zcr": 0.006103515625
    },
    {
        "index": 733,
        "zcr": 0.008544921875
    },
    {
        "index": 734,
        "zcr": 0.010009765625
    },
    {
        "index": 735,
        "zcr": 0.013916015625
    },
    {
        "index": 736,
        "zcr": 0.028076171875
    },
    {
        "index": 737,
        "zcr": 0.0283203125
    },
    {
        "index": 738,
        "zcr": 0.0263671875
    },
    {
        "index": 739,
        "zcr": 0.03125
    },
    {
        "index": 740,
        "zcr": 0.02685546875
    },
    {
        "index": 741,
        "zcr": 0.026611328125
    },
    {
        "index": 742,
        "zcr": 0.080078125
    },
    {
        "index": 743,
        "zcr": 0.082763671875
    },
    {
        "index": 744,
        "zcr": 0.0380859375
    },
    {
        "index": 745,
        "zcr": 0.031982421875
    },
    {
        "index": 746,
        "zcr": 0.02734375
    },
    {
        "index": 747,
        "zcr": 0.033203125
    },
    {
        "index": 748,
        "zcr": 0.034912109375
    },
    {
        "index": 749,
        "zcr": 0.04638671875
    },
    {
        "index": 750,
        "zcr": 0.04833984375
    },
    {
        "index": 751,
        "zcr": 0.037353515625
    },
    {
        "index": 752,
        "zcr": 0.0078125
    },
    {
        "index": 753,
        "zcr": 0.0078125
    },
    {
        "index": 754,
        "zcr": 0.002197265625
    },
    {
        "index": 755,
        "zcr": 0.00634765625
    },
    {
        "index": 756,
        "zcr": 0.008544921875
    },
    {
        "index": 757,
        "zcr": 0.008056640625
    },
    {
        "index": 758,
        "zcr": 0.010498046875
    },
    {
        "index": 759,
        "zcr": 0.010498046875
    },
    {
        "index": 760,
        "zcr": 0.01171875
    },
    {
        "index": 761,
        "zcr": 0.010986328125
    },
    {
        "index": 762,
        "zcr": 0.019775390625
    },
    {
        "index": 763,
        "zcr": 0.088134765625
    },
    {
        "index": 764,
        "zcr": 0.072998046875
    },
    {
        "index": 765,
        "zcr": 0.02490234375
    },
    {
        "index": 766,
        "zcr": 0.02001953125
    },
    {
        "index": 767,
        "zcr": 0.01416015625
    },
    {
        "index": 768,
        "zcr": 0.008056640625
    },
    {
        "index": 769,
        "zcr": 0.006103515625
    },
    {
        "index": 770,
        "zcr": 0.01318359375
    },
    {
        "index": 770,
        "zcr": 0.01318359375
    },
    {
        "index": 772,
        "zcr": 0.013916015625
    },
    {
        "index": 773,
        "zcr": 0.0068359375
    },
    {
        "index": 774,
        "zcr": 0.005615234375
    },
    {
        "index": 775,
        "zcr": 0.006591796875
    },
    {
        "index": 776,
        "zcr": 0.01025390625
    },
    {
        "index": 777,
        "zcr": 0.01708984375
    },
    {
        "index": 778,
        "zcr": 0.0341796875
    },
    {
        "index": 779,
        "zcr": 0.03125
    },
    {
        "index": 780,
        "zcr": 0.024658203125
    },
    {
        "index": 781,
        "zcr": 0.034912109375
    },
    {
        "index": 782,
        "zcr": 0.0400390625
    },
    {
        "index": 783,
        "zcr": 0.029541015625
    },
    {
        "index": 784,
        "zcr": 0.0830078125
    },
    {
        "index": 785,
        "zcr": 0.0634765625
    },
    {
        "index": 786,
        "zcr": 0.0302734375
    },
    {
        "index": 787,
        "zcr": 0.02783203125
    },
    {
        "index": 788,
        "zcr": 0.0361328125
    },
    {
        "index": 789,
        "zcr": 0.0322265625
    },
    {
        "index": 790,
        "zcr": 0.03662109375
    },
    {
        "index": 791,
        "zcr": 0.031494140625
    },
    {
        "index": 792,
        "zcr": 0.030517578125
    },
    {
        "index": 793,
        "zcr": 0.01806640625
    },
    {
        "index": 794,
        "zcr": 0.00537109375
    },
    {
        "index": 795,
        "zcr": 0.00830078125
    },
    {
        "index": 796,
        "zcr": 0.00537109375
    },
    {
        "index": 797,
        "zcr": 0.005859375
    },
    {
        "index": 798,
        "zcr": 0.01318359375
    },
    {
        "index": 799,
        "zcr": 0.009765625
    },
    {
        "index": 800,
        "zcr": 0.011474609375
    },
    {
        "index": 801,
        "zcr": 0.008056640625
    },
    {
        "index": 802,
        "zcr": 0.0087890625
    },
    {
        "index": 803,
        "zcr": 0.01123046875
    },
    {
        "index": 804,
        "zcr": 0.044677734375
    },
    {
        "index": 805,
        "zcr": 0.103515625
    },
    {
        "index": 806,
        "zcr": 0.048583984375
    },
    {
        "index": 807,
        "zcr": 0.0234375
    },
    {
        "index": 808,
        "zcr": 0.02099609375
    },
    {
        "index": 809,
        "zcr": 0.01513671875
    },
    {
        "index": 810,
        "zcr": 0.008056640625
    },
    {
        "index": 811,
        "zcr": 0.012451171875
    },
    {
        "index": 812,
        "zcr": 0.01171875
    },
    {
        "index": 813,
        "zcr": 0.00830078125
    },
    {
        "index": 814,
        "zcr": 0.01220703125
    },
    {
        "index": 815,
        "zcr": 0.00439453125
    },
    {
        "index": 816,
        "zcr": 0.006591796875
    },
    {
        "index": 817,
        "zcr": 0.008544921875
    },
    {
        "index": 818,
        "zcr": 0.01416015625
    },
    {
        "index": 818,
        "zcr": 0.01416015625
    },
    {
        "index": 820,
        "zcr": 0.03125
    },
    {
        "index": 821,
        "zcr": 0.02783203125
    },
    {
        "index": 822,
        "zcr": 0.018310546875
    },
    {
        "index": 823,
        "zcr": 0.029296875
    },
    {
        "index": 824,
        "zcr": 0.023681640625
    },
    {
        "index": 825,
        "zcr": 0.03466796875
    },
    {
        "index": 826,
        "zcr": 0.075927734375
    },
    {
        "index": 827,
        "zcr": 0.048583984375
    },
    {
        "index": 828,
        "zcr": 0.03173828125
    },
    {
        "index": 829,
        "zcr": 0.030517578125
    },
    {
        "index": 830,
        "zcr": 0.0322265625
    },
    {
        "index": 831,
        "zcr": 0.03857421875
    },
    {
        "index": 832,
        "zcr": 0.036376953125
    },
    {
        "index": 833,
        "zcr": 0.0478515625
    },
    {
        "index": 834,
        "zcr": 0.04345703125
    },
    {
        "index": 835,
        "zcr": 0.00439453125
    },
    {
        "index": 836,
        "zcr": 0.01806640625
    },
    {
        "index": 837,
        "zcr": 0.022705078125
    },
    {
        "index": 838,
        "zcr": 0.008544921875
    },
    {
        "index": 839,
        "zcr": 0.021484375
    },
    {
        "index": 840,
        "zcr": 0.012939453125
    },
    {
        "index": 841,
        "zcr": 0.056640625
    },
    {
        "index": 842,
        "zcr": 0.068115234375
    },
    {
        "index": 843,
        "zcr": 0.054443359375
    },
    {
        "index": 844,
        "zcr": 0.039306640625
    },
    {
        "index": 845,
        "zcr": 0.027099609375
    },
    {
        "index": 846,
        "zcr": 0.0517578125
    },
    {
        "index": 847,
        "zcr": 0.069091796875
    },
    {
        "index": 848,
        "zcr": 0.042724609375
    },
    {
        "index": 849,
        "zcr": 0.04248046875
    },
    {
        "index": 850,
        "zcr": 0.02685546875
    },
    {
        "index": 851,
        "zcr": 0.009765625
    },
    {
        "index": 852,
        "zcr": 0.0078125
    },
    {
        "index": 853,
        "zcr": 0.01318359375
    },
    {
        "index": 854,
        "zcr": 0.043701171875
    },
    {
        "index": 855,
        "zcr": 0.03271484375
    },
    {
        "index": 856,
        "zcr": 0.0029296875
    },
    {
        "index": 857,
        "zcr": 0.01904296875
    },
    {
        "index": 858,
        "zcr": 0.0224609375
    },
    {
        "index": 859,
        "zcr": 0.02001953125
    },
    {
        "index": 860,
        "zcr": 0.03955078125
    },
    {
        "index": 861,
        "zcr": 0.02392578125
    },
    {
        "index": 861,
        "zcr": 0.02392578125
    },
    {
        "index": 863,
        "zcr": 0.029541015625
    },
    {
        "index": 864,
        "zcr": 0.01220703125
    },
    {
        "index": 865,
        "zcr": 0.03125
    },
    {
        "index": 866,
        "zcr": 0.02392578125
    },
    {
        "index": 867,
        "zcr": 0.0712890625
    },
    {
        "index": 868,
        "zcr": 0.09326171875
    },
    {
        "index": 869,
        "zcr": 0.01513671875
    },
    {
        "index": 870,
        "zcr": 0.018798828125
    },
    {
        "index": 871,
        "zcr": 0.023193359375
    },
    {
        "index": 872,
        "zcr": 0.045166015625
    },
    {
        "index": 873,
        "zcr": 0.10693359375
    },
    {
        "index": 874,
        "zcr": 0.05615234375
    },
    {
        "index": 875,
        "zcr": 0.097412109375
    },
    {
        "index": 876,
        "zcr": 0.0703125
    },
    {
        "index": 877,
        "zcr": 0.021240234375
    },
    {
        "index": 878,
        "zcr": 0.074462890625
    },
    {
        "index": 879,
        "zcr": 0.031494140625
    },
    {
        "index": 880,
        "zcr": 0.03125
    },
    {
        "index": 881,
        "zcr": 0.012451171875
    },
    {
        "index": 882,
        "zcr": 0.00732421875
    },
    {
        "index": 883,
        "zcr": 0.0068359375
    },
    {
        "index": 884,
        "zcr": 0.005126953125
    },
    {
        "index": 885,
        "zcr": 0.008056640625
    },
    {
        "index": 886,
        "zcr": 0.01220703125
    },
    {
        "index": 887,
        "zcr": 0.022216796875
    },
    {
        "index": 888,
        "zcr": 0.0654296875
    },
    {
        "index": 889,
        "zcr": 0.073486328125
    },
    {
        "index": 890,
        "zcr": 0.0185546875
    },
    {
        "index": 891,
        "zcr": 0.032470703125
    },
    {
        "index": 892,
        "zcr": 0.0185546875
    },
    {
        "index": 893,
        "zcr": 0.008544921875
    },
    {
        "index": 894,
        "zcr": 0.0078125
    },
    {
        "index": 895,
        "zcr": 0.020263671875
    },
    {
        "index": 896,
        "zcr": 0.014404296875
    },
    {
        "index": 897,
        "zcr": 0.029296875
    },
    {
        "index": 898,
        "zcr": 0.00390625
    },
    {
        "index": 899,
        "zcr": 0.004150390625
    },
    {
        "index": 900,
        "zcr": 0.006103515625
    },
    {
        "index": 900,
        "zcr": 0.006103515625
    },
    {
        "index": 901,
        "zcr": 0.00830078125
    },
    {
        "index": 903,
        "zcr": 0.03369140625
    },
    {
        "index": 904,
        "zcr": 0.03125
    },
    {
        "index": 905,
        "zcr": 0.01806640625
    },
    {
        "index": 906,
        "zcr": 0.008056640625
    },
    {
        "index": 907,
        "zcr": 0.01220703125
    },
    {
        "index": 908,
        "zcr": 0.025390625
    },
    {
        "index": 909,
        "zcr": 0.072265625
    },
    {
        "index": 910,
        "zcr": 0.086181640625
    },
    {
        "index": 911,
        "zcr": 0.051513671875
    },
    {
        "index": 912,
        "zcr": 0.057861328125
    },
    {
        "index": 913,
        "zcr": 0.038818359375
    },
    {
        "index": 914,
        "zcr": 0.012939453125
    },
    {
        "index": 915,
        "zcr": 0.02490234375
    },
    {
        "index": 916,
        "zcr": 0.035888671875
    },
    {
        "index": 917,
        "zcr": 0.0244140625
    },
    {
        "index": 918,
        "zcr": 0.02490234375
    },
    {
        "index": 919,
        "zcr": 0.01611328125
    },
    {
        "index": 920,
        "zcr": 0.074462890625
    },
    {
        "index": 921,
        "zcr": 0.049560546875
    },
    {
        "index": 922,
        "zcr": 0.02001953125
    },
    {
        "index": 923,
        "zcr": 0.011962890625
    },
    {
        "index": 924,
        "zcr": 0.0126953125
    },
    {
        "index": 925,
        "zcr": 0.0068359375
    },
    {
        "index": 926,
        "zcr": 0.004150390625
    },
    {
        "index": 927,
        "zcr": 0.012451171875
    },
    {
        "index": 928,
        "zcr": 0.01220703125
    },
    {
        "index": 929,
        "zcr": 0.033203125
    },
    {
        "index": 930,
        "zcr": 0.093994140625
    },
    {
        "index": 931,
        "zcr": 0.0615234375
    },
    {
        "index": 932,
        "zcr": 0.035400390625
    },
    {
        "index": 933,
        "zcr": 0.03662109375
    },
    {
        "index": 934,
        "zcr": 0.010986328125
    },
    {
        "index": 935,
        "zcr": 0.01123046875
    },
    {
        "index": 936,
        "zcr": 0.011474609375
    },
    {
        "index": 937,
        "zcr": 0.013671875
    },
    {
        "index": 938,
        "zcr": 0.00390625
    },
    {
        "index": 939,
        "zcr": 0.011474609375
    },
    {
        "index": 940,
        "zcr": 0.010009765625
    },
    {
        "index": 941,
        "zcr": 0.002685546875
    },
    {
        "index": 942,
        "zcr": 0.010498046875
    },
    {
        "index": 943,
        "zcr": 0.012939453125
    },
    {
        "index": 944,
        "zcr": 0.021484375
    },
    {
        "index": 945,
        "zcr": 0.030517578125
    },
    {
        "index": 946,
        "zcr": 0.0439453125
    },
    {
        "index": 947,
        "zcr": 0.073974609375
    },
    {
        "index": 948,
        "zcr": 0.07958984375
    },
    {
        "index": 949,
        "zcr": 0.07763671875
    },
    {
        "index": 950,
        "zcr": 0.04833984375
    },
    {
        "index": 951,
        "zcr": 0.11474609375
    },
    {
        "index": 952,
        "zcr": 0.019775390625
    },
    {
        "index": 953,
        "zcr": 0.002197265625
    },
    {
        "index": 954,
        "zcr": 0.00244140625
    },
    {
        "index": 955,
        "zcr": 0.0048828125
    },
    {
        "index": 956,
        "zcr": 0.003662109375
    },
    {
        "index": 957,
        "zcr": 0.008056640625
    },
    {
        "index": 958,
        "zcr": 0.006103515625
    },
    {
        "index": 959,
        "zcr": 0.017578125
    },
    {
        "index": 960,
        "zcr": 0.017578125
    },
    {
        "index": 961,
        "zcr": 0.06103515625
    },
    {
        "index": 962,
        "zcr": 0.03076171875
    },
    {
        "index": 963,
        "zcr": 0.0498046875
    },
    {
        "index": 964,
        "zcr": 0.0126953125
    },
    {
        "index": 965,
        "zcr": 0.008544921875
    },
    {
        "index": 966,
        "zcr": 0.008056640625
    },
    {
        "index": 967,
        "zcr": 0.010009765625
    },
    {
        "index": 968,
        "zcr": 0.007568359375
    },
    {
        "index": 969,
        "zcr": 0.0078125
    },
    {
        "index": 970,
        "zcr": 0.013671875
    },
    {
        "index": 971,
        "zcr": 0.04638671875
    },
    {
        "index": 972,
        "zcr": 0.0888671875
    },
    {
        "index": 973,
        "zcr": 0.014892578125
    },
    {
        "index": 974,
        "zcr": 0.033203125
    },
    {
        "index": 975,
        "zcr": 0.031005859375
    },
    {
        "index": 976,
        "zcr": 0.010986328125
    },
    {
        "index": 977,
        "zcr": 0.00537109375
    },
    {
        "index": 978,
        "zcr": 0.01904296875
    },
    {
        "index": 979,
        "zcr": 0.01513671875
    },
    {
        "index": 980,
        "zcr": 0.031005859375
    },
    {
        "index": 981,
        "zcr": 0.00537109375
    },
    {
        "index": 982,
        "zcr": 0.00244140625
    },
    {
        "index": 983,
        "zcr": 0.0068359375
    },
    {
        "index": 984,
        "zcr": 0.0078125
    },
    {
        "index": 985,
        "zcr": 0.008056640625
    },
    {
        "index": 986,
        "zcr": 0.025390625
    },
    {
        "index": 987,
        "zcr": 0.03173828125
    },
    {
        "index": 988,
        "zcr": 0.030029296875
    },
    {
        "index": 989,
        "zcr": 0.007568359375
    },
    {
        "index": 990,
        "zcr": 0.00830078125
    },
    {
        "index": 991,
        "zcr": 0.01611328125
    },
    {
        "index": 992,
        "zcr": 0.057861328125
    },
    {
        "index": 993,
        "zcr": 0.111572265625
    },
    {
        "index": 994,
        "zcr": 0.0263671875
    },
    {
        "index": 995,
        "zcr": 0.02001953125
    },
    {
        "index": 996,
        "zcr": 0.01953125
    },
    {
        "index": 996,
        "zcr": 0.01953125
    },
    {
        "index": 998,
        "zcr": 0.0263671875
    },
    {
        "index": 999,
        "zcr": 0.026123046875
    },
    {
        "index": 1000,
        "zcr": 0.030029296875
    },
    {
        "index": 1001,
        "zcr": 0.029296875
    },
    {
        "index": 1002,
        "zcr": 0.006103515625
    },
    {
        "index": 1003,
        "zcr": 0.007080078125
    },
    {
        "index": 1004,
        "zcr": 0.006103515625
    },
    {
        "index": 1005,
        "zcr": 0.012939453125
    },
    {
        "index": 1006,
        "zcr": 0.014404296875
    },
    {
        "index": 1007,
        "zcr": 0.02734375
    },
    {
        "index": 1008,
        "zcr": 0.03466796875
    },
    {
        "index": 1009,
        "zcr": 0.0341796875
    },
    {
        "index": 1010,
        "zcr": 0.0302734375
    },
    {
        "index": 1011,
        "zcr": 0.02783203125
    },
    {
        "index": 1012,
        "zcr": 0.0146484375
    },
    {
        "index": 1013,
        "zcr": 0.005126953125
    },
    {
        "index": 1014,
        "zcr": 0.008056640625
    },
    {
        "index": 1015,
        "zcr": 0.009765625
    },
    {
        "index": 1016,
        "zcr": 0.005615234375
    },
    {
        "index": 1017,
        "zcr": 0.0185546875
    },
    {
        "index": 1018,
        "zcr": 0.03369140625
    },
    {
        "index": 1019,
        "zcr": 0.03125
    },
    {
        "index": 1020,
        "zcr": 0.023193359375
    },
    {
        "index": 1021,
        "zcr": 0.037109375
    },
    {
        "index": 1022,
        "zcr": 0.051513671875
    },
    {
        "index": 1023,
        "zcr": 0.0048828125
    },
    {
        "index": 1024,
        "zcr": 0.002685546875
    },
    {
        "index": 1025,
        "zcr": 0.00439453125
    },
    {
        "index": 1026,
        "zcr": 0.01171875
    },
    {
        "index": 1027,
        "zcr": 0.008056640625
    },
    {
        "index": 1028,
        "zcr": 0.0302734375
    },
    {
        "index": 1029,
        "zcr": 0.033935546875
    },
    {
        "index": 1030,
        "zcr": 0.02685546875
    },
    {
        "index": 1031,
        "zcr": 0.03369140625
    },
    {
        "index": 1032,
        "zcr": 0.03271484375
    },
    {
        "index": 1033,
        "zcr": 0.0078125
    },
    {
        "index": 1034,
        "zcr": 0.0048828125
    },
    {
        "index": 1035,
        "zcr": 0.004150390625
    },
    {
        "index": 1036,
        "zcr": 0.00830078125
    },
    {
        "index": 1037,
        "zcr": 0.00732421875
    },
    {
        "index": 1038,
        "zcr": 0.03076171875
    },
    {
        "index": 1039,
        "zcr": 0.02880859375
    },
    {
        "index": 1040,
        "zcr": 0.02880859375
    },
    {
        "index": 1041,
        "zcr": 0.025146484375
    },
    {
        "index": 1042,
        "zcr": 0.042236328125
    },
    {
        "index": 1043,
        "zcr": 0.0302734375
    },
    {
        "index": 1044,
        "zcr": 0.03125
    },
    {
        "index": 1045,
        "zcr": 0.037109375
    },
    {
        "index": 1046,
        "zcr": 0.04296875
    },
    {
        "index": 1047,
        "zcr": 0.025146484375
    },
    {
        "index": 1048,
        "zcr": 0.01611328125
    },
    {
        "index": 1049,
        "zcr": 0.0107421875
    },
    {
        "index": 1050,
        "zcr": 0.008544921875
    },
    {
        "index": 1051,
        "zcr": 0.0048828125
    },
    {
        "index": 1052,
        "zcr": 0.009765625
    },
    {
        "index": 1053,
        "zcr": 0.01220703125
    },
    {
        "index": 1054,
        "zcr": 0.031982421875
    },
    {
        "index": 1055,
        "zcr": 0.093994140625
    },
    {
        "index": 1056,
        "zcr": 0.06591796875
    },
    {
        "index": 1057,
        "zcr": 0.04150390625
    },
    {
        "index": 1058,
        "zcr": 0.031982421875
    },
    {
        "index": 1059,
        "zcr": 0.01025390625
    },
    {
        "index": 1060,
        "zcr": 0.009521484375
    },
    {
        "index": 1061,
        "zcr": 0.01220703125
    },
    {
        "index": 1062,
        "zcr": 0.01318359375
    },
    {
        "index": 1063,
        "zcr": 0.013916015625
    },
    {
        "index": 1064,
        "zcr": 0.014892578125
    },
    {
        "index": 1065,
        "zcr": 0.004150390625
    },
    {
        "index": 1066,
        "zcr": 0.001708984375
    },
    {
        "index": 1067,
        "zcr": 0.00927734375
    },
    {
        "index": 1068,
        "zcr": 0.0146484375
    },
    {
        "index": 1069,
        "zcr": 0.01806640625
    },
    {
        "index": 1070,
        "zcr": 0.031982421875
    },
    {
        "index": 1071,
        "zcr": 0.030517578125
    },
    {
        "index": 1072,
        "zcr": 0.0126953125
    },
    {
        "index": 1073,
        "zcr": 0.008056640625
    },
    {
        "index": 1074,
        "zcr": 0.013427734375
    },
    {
        "index": 1075,
        "zcr": 0.043212890625
    },
    {
        "index": 1076,
        "zcr": 0.10498046875
    },
    {
        "index": 1077,
        "zcr": 0.076171875
    },
    {
        "index": 1078,
        "zcr": 0.04541015625
    },
    {
        "index": 1079,
        "zcr": 0.05859375
    },
    {
        "index": 1080,
        "zcr": 0.029052734375
    },
    {
        "index": 1081,
        "zcr": 0.006591796875
    },
    {
        "index": 1082,
        "zcr": 0.02734375
    },
    {
        "index": 1083,
        "zcr": 0.04052734375
    },
    {
        "index": 1084,
        "zcr": 0.021484375
    },
    {
        "index": 1085,
        "zcr": 0.01611328125
    },
    {
        "index": 1086,
        "zcr": 0.056884765625
    },
    {
        "index": 1087,
        "zcr": 0.02294921875
    },
    {
        "index": 1088,
        "zcr": 0.028564453125
    },
    {
        "index": 1089,
        "zcr": 0.011474609375
    },
    {
        "index": 1090,
        "zcr": 0.015869140625
    },
    {
        "index": 1091,
        "zcr": 0.005859375
    },
    {
        "index": 1092,
        "zcr": 0.00732421875
    },
    {
        "index": 1093,
        "zcr": 0.005615234375
    },
    {
        "index": 1094,
        "zcr": 0.011962890625
    },
    {
        "index": 1095,
        "zcr": 0.0146484375
    },
    {
        "index": 1096,
        "zcr": 0.056640625
    },
    {
        "index": 1097,
        "zcr": 0.087890625
    },
    {
        "index": 1098,
        "zcr": 0.02880859375
    },
    {
        "index": 1099,
        "zcr": 0.030517578125
    },
    {
        "index": 1100,
        "zcr": 0.027099609375
    },
    {
        "index": 1101,
        "zcr": 0.009521484375
    },
    {
        "index": 1102,
        "zcr": 0.009521484375
    },
    {
        "index": 1103,
        "zcr": 0.01611328125
    },
    {
        "index": 1104,
        "zcr": 0.01123046875
    },
    {
        "index": 1105,
        "zcr": 0.01123046875
    },
    {
        "index": 1106,
        "zcr": 0.00537109375
    },
    {
        "index": 1107,
        "zcr": 0.0048828125
    },
    {
        "index": 1108,
        "zcr": 0.0068359375
    },
    {
        "index": 1109,
        "zcr": 0.004150390625
    },
    {
        "index": 1110,
        "zcr": 0.01123046875
    },
    {
        "index": 1111,
        "zcr": 0.028076171875
    },
    {
        "index": 1112,
        "zcr": 0.03173828125
    },
    {
        "index": 1113,
        "zcr": 0.05029296875
    },
    {
        "index": 1114,
        "zcr": 0.087158203125
    },
    {
        "index": 1115,
        "zcr": 0.069580078125
    },
    {
        "index": 1116,
        "zcr": 0.037841796875
    },
    {
        "index": 1117,
        "zcr": 0.0712890625
    },
    {
        "index": 1118,
        "zcr": 0.10205078125
    },
    {
        "index": 1119,
        "zcr": 0.0029296875
    },
    {
        "index": 1120,
        "zcr": 0.002685546875
    },
    {
        "index": 1121,
        "zcr": 0.004150390625
    },
    {
        "index": 1122,
        "zcr": 0.00537109375
    },
    {
        "index": 1122,
        "zcr": 0.00537109375
    },
    {
        "index": 1124,
        "zcr": 0.0048828125
    },
    {
        "index": 1125,
        "zcr": 0.001708984375
    },
    {
        "index": 1126,
        "zcr": 0.013427734375
    },
    {
        "index": 1127,
        "zcr": 0.00927734375
    },
    {
        "index": 1128,
        "zcr": 0.067138671875
    },
    {
        "index": 1129,
        "zcr": 0.044921875
    },
    {
        "index": 1130,
        "zcr": 0.02978515625
    },
    {
        "index": 1131,
        "zcr": 0.021484375
    },
    {
        "index": 1132,
        "zcr": 0.005126953125
    },
    {
        "index": 1133,
        "zcr": 0.010498046875
    },
    {
        "index": 1134,
        "zcr": 0.008544921875
    },
    {
        "index": 1135,
        "zcr": 0.0126953125
    },
    {
        "index": 1136,
        "zcr": 0.006103515625
    },
    {
        "index": 1137,
        "zcr": 0.02294921875
    },
    {
        "index": 1138,
        "zcr": 0.075439453125
    },
    {
        "index": 1139,
        "zcr": 0.09326171875
    },
    {
        "index": 1140,
        "zcr": 0.035888671875
    },
    {
        "index": 1141,
        "zcr": 0.034423828125
    },
    {
        "index": 1142,
        "zcr": 0.021484375
    },
    {
        "index": 1143,
        "zcr": 0.00830078125
    },
    {
        "index": 1144,
        "zcr": 0.005615234375
    },
    {
        "index": 1145,
        "zcr": 0.02783203125
    },
    {
        "index": 1146,
        "zcr": 0.01416015625
    },
    {
        "index": 1147,
        "zcr": 0.018310546875
    },
    {
        "index": 1148,
        "zcr": 0.00341796875
    },
    {
        "index": 1149,
        "zcr": 0.007568359375
    },
    {
        "index": 1150,
        "zcr": 0.005859375
    },
    {
        "index": 1151,
        "zcr": 0.01318359375
    },
    {
        "index": 1152,
        "zcr": 0.015869140625
    },
    {
        "index": 1153,
        "zcr": 0.02978515625
    },
    {
        "index": 1154,
        "zcr": 0.03271484375
    },
    {
        "index": 1155,
        "zcr": 0.0205078125
    },
    {
        "index": 1156,
        "zcr": 0.010009765625
    },
    {
        "index": 1157,
        "zcr": 0.0126953125
    },
    {
        "index": 1158,
        "zcr": 0.019287109375
    },
    {
        "index": 1159,
        "zcr": 0.07470703125
    },
    {
        "index": 1160,
        "zcr": 0.08251953125
    },
    {
        "index": 1161,
        "zcr": 0.022216796875
    },
    {
        "index": 1162,
        "zcr": 0.01513671875
    },
    {
        "index": 1163,
        "zcr": 0.0224609375
    },
    {
        "index": 1164,
        "zcr": 0.02392578125
    },
    {
        "index": 1165,
        "zcr": 0.025390625
    },
    {
        "index": 1166,
        "zcr": 0.02490234375
    },
    {
        "index": 1167,
        "zcr": 0.02978515625
    },
    {
        "index": 1168,
        "zcr": 0.0224609375
    },
    {
        "index": 1169,
        "zcr": 0.00390625
    },
    {
        "index": 1170,
        "zcr": 0.00439453125
    },
    {
        "index": 1171,
        "zcr": 0.0078125
    },
    {
        "index": 1172,
        "zcr": 0.010009765625
    },
    {
        "index": 1173,
        "zcr": 0.02001953125
    },
    {
        "index": 1174,
        "zcr": 0.03173828125
    },
    {
        "index": 1175,
        "zcr": 0.029052734375
    },
    {
        "index": 1176,
        "zcr": 0.025634765625
    },
    {
        "index": 1177,
        "zcr": 0.020263671875
    },
    {
        "index": 1178,
        "zcr": 0.0380859375
    },
    {
        "index": 1179,
        "zcr": 0.003662109375
    },
    {
        "index": 1180,
        "zcr": 0.00537109375
    },
    {
        "index": 1181,
        "zcr": 0.00341796875
    },
    {
        "index": 1182,
        "zcr": 0.00732421875
    },
    {
        "index": 1183,
        "zcr": 0.008056640625
    },
    {
        "index": 1184,
        "zcr": 0.023193359375
    },
    {
        "index": 1185,
        "zcr": 0.034912109375
    },
    {
        "index": 1186,
        "zcr": 0.029541015625
    },
    {
        "index": 1187,
        "zcr": 0.036376953125
    },
    {
        "index": 1188,
        "zcr": 0.03369140625
    },
    {
        "index": 1189,
        "zcr": 0.02099609375
    },
    {
        "index": 1190,
        "zcr": 0.005615234375
    },
    {
        "index": 1191,
        "zcr": 0.0029296875
    },
    {
        "index": 1192,
        "zcr": 0.005859375
    },
    {
        "index": 1193,
        "zcr": 0.0068359375
    },
    {
        "index": 1194,
        "zcr": 0.01220703125
    },
    {
        "index": 1195,
        "zcr": 0.035400390625
    },
    {
        "index": 1196,
        "zcr": 0.033935546875
    },
    {
        "index": 1197,
        "zcr": 0.02587890625
    },
    {
        "index": 1198,
        "zcr": 0.035888671875
    },
    {
        "index": 1199,
        "zcr": 0.026123046875
    },
    {
        "index": 1200,
        "zcr": 0.0029296875
    },
    {
        "index": 1201,
        "zcr": 0.006103515625
    },
    {
        "index": 1202,
        "zcr": 0.01171875
    },
    {
        "index": 1203,
        "zcr": 0.01416015625
    },
    {
        "index": 1204,
        "zcr": 0.01220703125
    },
    {
        "index": 1205,
        "zcr": 0.031005859375
    },
    {
        "index": 1206,
        "zcr": 0.02587890625
    },
    {
        "index": 1207,
        "zcr": 0.028076171875
    },
    {
        "index": 1208,
        "zcr": 0.031982421875
    },
    {
        "index": 1209,
        "zcr": 0.037353515625
    },
    {
        "index": 1210,
        "zcr": 0.022216796875
    },
    {
        "index": 1211,
        "zcr": 0.0576171875
    },
    {
        "index": 1212,
        "zcr": 0.029296875
    },
    {
        "index": 1213,
        "zcr": 0.046630859375
    },
    {
        "index": 1214,
        "zcr": 0.018798828125
    },
    {
        "index": 1215,
        "zcr": 0.016845703125
    },
    {
        "index": 1216,
        "zcr": 0.00634765625
    },
    {
        "index": 1217,
        "zcr": 0.00830078125
    },
    {
        "index": 1218,
        "zcr": 0.004638671875
    },
    {
        "index": 1219,
        "zcr": 0.0087890625
    },
    {
        "index": 1220,
        "zcr": 0.012451171875
    },
    {
        "index": 1221,
        "zcr": 0.048828125
    },
    {
        "index": 1222,
        "zcr": 0.097412109375
    },
    {
        "index": 1223,
        "zcr": 0.042724609375
    },
    {
        "index": 1224,
        "zcr": 0.027099609375
    },
    {
        "index": 1225,
        "zcr": 0.028564453125
    },
    {
        "index": 1226,
        "zcr": 0.00927734375
    },
    {
        "index": 1227,
        "zcr": 0.009765625
    },
    {
        "index": 1228,
        "zcr": 0.01318359375
    },
    {
        "index": 1229,
        "zcr": 0.011962890625
    },
    {
        "index": 1230,
        "zcr": 0.0185546875
    },
    {
        "index": 1231,
        "zcr": 0.004638671875
    },
    {
        "index": 1232,
        "zcr": 0.010009765625
    },
    {
        "index": 1233,
        "zcr": 0.005126953125
    },
    {
        "index": 1234,
        "zcr": 0.009765625
    },
    {
        "index": 1235,
        "zcr": 0.00439453125
    },
    {
        "index": 1236,
        "zcr": 0.0234375
    },
    {
        "index": 1237,
        "zcr": 0.02392578125
    },
    {
        "index": 1238,
        "zcr": 0.010009765625
    },
    {
        "index": 1239,
        "zcr": 0.013671875
    },
    {
        "index": 1240,
        "zcr": 0.00146484375
    },
    {
        "index": 1241,
        "zcr": 0.012451171875
    },
    {
        "index": 1242,
        "zcr": 0.004638671875
    },
    {
        "index": 1243,
        "zcr": 0.005126953125
    },
    {
        "index": 1244,
        "zcr": 0.006591796875
    },
    {
        "index": 1245,
        "zcr": 0.004150390625
    },
    {
        "index": 1246,
        "zcr": 0.0458984375
    },
    {
        "index": 1247,
        "zcr": 0.0283203125
    },
    {
        "index": 1248,
        "zcr": 0.01416015625
    },
    {
        "index": 1249,
        "zcr": 0.03125
    },
    {
        "index": 1250,
        "zcr": 0.040283203125
    },
    {
        "index": 1251,
        "zcr": 0.01953125
    },
    {
        "index": 1252,
        "zcr": 0.01220703125
    },
    {
        "index": 1253,
        "zcr": 0.0595703125
    },
    {
        "index": 1254,
        "zcr": 0.0400390625
    },
    {
        "index": 1255,
        "zcr": 0.04150390625
    },
    {
        "index": 1256,
        "zcr": 0.0146484375
    },
    {
        "index": 1257,
        "zcr": 0.007080078125
    },
    {
        "index": 1258,
        "zcr": 0.0078125
    },
    {
        "index": 1259,
        "zcr": 0.0048828125
    },
    {
        "index": 1260,
        "zcr": 0.006591796875
    },
    {
        "index": 1261,
        "zcr": 0.009033203125
    },
    {
        "index": 1262,
        "zcr": 0.020263671875
    },
    {
        "index": 1263,
        "zcr": 0.07763671875
    },
    {
        "index": 1264,
        "zcr": 0.08544921875
    },
    {
        "index": 1265,
        "zcr": 0.01220703125
    },
    {
        "index": 1266,
        "zcr": 0.03173828125
    },
    {
        "index": 1267,
        "zcr": 0.02099609375
    },
    {
        "index": 1268,
        "zcr": 0.014404296875
    },
    {
        "index": 1269,
        "zcr": 0.01123046875
    },
    {
        "index": 1270,
        "zcr": 0.016845703125
    },
    {
        "index": 1271,
        "zcr": 0.00439453125
    },
    {
        "index": 1272,
        "zcr": 0.01611328125
    },
    {
        "index": 1273,
        "zcr": 0.0029296875
    },
    {
        "index": 1274,
        "zcr": 0.0048828125
    },
    {
        "index": 1275,
        "zcr": 0.0068359375
    },
    {
        "index": 1276,
        "zcr": 0.0087890625
    },
    {
        "index": 1277,
        "zcr": 0.01025390625
    },
    {
        "index": 1278,
        "zcr": 0.0302734375
    },
    {
        "index": 1279,
        "zcr": 0.02734375
    },
    {
        "index": 1280,
        "zcr": 0.062255859375
    },
    {
        "index": 1281,
        "zcr": 0.0751953125
    },
    {
        "index": 1282,
        "zcr": 0.08984375
    },
    {
        "index": 1283,
        "zcr": 0.022216796875
    },
    {
        "index": 1284,
        "zcr": 0.103515625
    },
    {
        "index": 1285,
        "zcr": 0.076416015625
    },
    {
        "index": 1286,
        "zcr": 0.0029296875
    },
    {
        "index": 1287,
        "zcr": 0.001708984375
    },
    {
        "index": 1288,
        "zcr": 0.004150390625
    },
    {
        "index": 1289,
        "zcr": 0.0068359375
    },
    {
        "index": 1290,
        "zcr": 0.0078125
    },
    {
        "index": 1291,
        "zcr": 0.001953125
    },
    {
        "index": 1292,
        "zcr": 0.00146484375
    },
    {
        "index": 1293,
        "zcr": 0.01953125
    },
    {
        "index": 1294,
        "zcr": 0.030029296875
    },
    {
        "index": 1295,
        "zcr": 0.04541015625
    },
    {
        "index": 1296,
        "zcr": 0.0419921875
    },
    {
        "index": 1297,
        "zcr": 0.0263671875
    },
    {
        "index": 1298,
        "zcr": 0.014892578125
    },
    {
        "index": 1299,
        "zcr": 0.00927734375
    },
    {
        "index": 1300,
        "zcr": 0.00927734375
    },
    {
        "index": 1301,
        "zcr": 0.005859375
    },
    {
        "index": 1302,
        "zcr": 0.0087890625
    },
    {
        "index": 1303,
        "zcr": 0.01025390625
    },
    {
        "index": 1304,
        "zcr": 0.0283203125
    },
    {
        "index": 1305,
        "zcr": 0.09033203125
    },
    {
        "index": 1306,
        "zcr": 0.05029296875
    },
    {
        "index": 1307,
        "zcr": 0.015625
    },
    {
        "index": 1308,
        "zcr": 0.0341796875
    },
    {
        "index": 1309,
        "zcr": 0.021240234375
    },
    {
        "index": 1310,
        "zcr": 0.010009765625
    },
    {
        "index": 1311,
        "zcr": 0.01416015625
    },
    {
        "index": 1312,
        "zcr": 0.013916015625
    },
    {
        "index": 1313,
        "zcr": 0.018310546875
    },
    {
        "index": 1314,
        "zcr": 0.019287109375
    },
    {
        "index": 1315,
        "zcr": 0.0087890625
    },
    {
        "index": 1316,
        "zcr": 0.00390625
    },
    {
        "index": 1317,
        "zcr": 0.01123046875
    },
    {
        "index": 1318,
        "zcr": 0.007568359375
    },
    {
        "index": 1319,
        "zcr": 0.017578125
    },
    {
        "index": 1320,
        "zcr": 0.03076171875
    },
    {
        "index": 1321,
        "zcr": 0.030517578125
    },
    {
        "index": 1322,
        "zcr": 0.012451171875
    },
    {
        "index": 1323,
        "zcr": 0.010009765625
    },
    {
        "index": 1324,
        "zcr": 0.01123046875
    },
    {
        "index": 1325,
        "zcr": 0.025146484375
    },
    {
        "index": 1326,
        "zcr": 0.0859375
    },
    {
        "index": 1327,
        "zcr": 0.062255859375
    },
    {
        "index": 1328,
        "zcr": 0.02783203125
    },
    {
        "index": 1329,
        "zcr": 0.01025390625
    },
    {
        "index": 1330,
        "zcr": 0.028076171875
    },
    {
        "index": 1331,
        "zcr": 0.024658203125
    },
    {
        "index": 1332,
        "zcr": 0.026123046875
    },
    {
        "index": 1333,
        "zcr": 0.025634765625
    },
    {
        "index": 1334,
        "zcr": 0.028076171875
    },
    {
        "index": 1335,
        "zcr": 0.015380859375
    },
    {
        "index": 1336,
        "zcr": 0.0078125
    },
    {
        "index": 1337,
        "zcr": 0.00830078125
    },
    {
        "index": 1338,
        "zcr": 0.01025390625
    },
    {
        "index": 1339,
        "zcr": 0.0068359375
    },
    {
        "index": 1340,
        "zcr": 0.01513671875
    },
    {
        "index": 1341,
        "zcr": 0.02490234375
    },
    {
        "index": 1342,
        "zcr": 0.020751953125
    },
    {
        "index": 1343,
        "zcr": 0.04345703125
    },
    {
        "index": 1344,
        "zcr": 0.0224609375
    },
    {
        "index": 1345,
        "zcr": 0.045654296875
    },
    {
        "index": 1346,
        "zcr": 0.00537109375
    },
    {
        "index": 1347,
        "zcr": 0.002685546875
    },
    {
        "index": 1348,
        "zcr": 0.00439453125
    },
    {
        "index": 1349,
        "zcr": 0.00830078125
    },
    {
        "index": 1350,
        "zcr": 0.007568359375
    },
    {
        "index": 1351,
        "zcr": 0.029052734375
    },
    {
        "index": 1352,
        "zcr": 0.033935546875
    },
    {
        "index": 1353,
        "zcr": 0.022705078125
    },
    {
        "index": 1354,
        "zcr": 0.033203125
    },
    {
        "index": 1355,
        "zcr": 0.02587890625
    },
    {
        "index": 1356,
        "zcr": 0.0048828125
    }
]